drivers/__init__.py
drivers/i2c_dev.py
rpi_i2c_lcd_python-2022.1.1.18.41.42.dist-info/METADATA
rpi_i2c_lcd_python-2022.1.1.18.41.42.dist-info/WHEEL
rpi_i2c_lcd_python-2022.1.1.18.41.42.dist-info/top_level.txt
rpi_i2c_lcd_python-2022.1.1.18.41.42.dist-info/RECORD
